[
  {
    "PersonID": "2F4322B9-D231-4D6C-89DA-EB0821467FBB",
    "PersonName": "Tory Oventon",
    "Email": "toventon0@ucla.edu",
    "DateOfBirth": "2009-09-11",
    "Gender": "Female",
    "Address": "Apt 841",
    "ReceiveNewsLetters": true,
    "CountryID": "0C5B9025-A178-422F-9772-B83CF42F3FBA"
  },
  {
    "PersonID": "A116271C-7443-4323-84C5-D41BA2D96BE9",
    "PersonName": "Rosy Hessay",
    "Email": "rhessay1@jalbum.net",
    "DateOfBirth": "1997-12-24",
    "Gender": "Female",
    "Address": "6th Floor",
    "ReceiveNewsLetters": false,
    "CountryID": "148FECC0-F5AA-43A1-9744-1DA4289C7A5A"
  },
  {
    "PersonID": "3B372230-D9B4-4952-99F4-3E9369FA0DB4",
    "PersonName": "Holly Fishlee",
    "Email": "hfishlee2@ucoz.com",
    "DateOfBirth": "1992-11-14",
    "Gender": "Male",
    "Address": "PO Box 5286",
    "ReceiveNewsLetters": true,
    "CountryID": "F7F1E057-CC8D-4C34-B03F-32387397DAA2"
  },
  {
    "PersonID": "B0DA6468-792D-4649-B1DD-62D6F9C22735",
    "PersonName": "Teresita Palleske",
    "Email": "tpalleske3@weibo.com",
    "DateOfBirth": "2015-12-18",
    "Gender": "Other",
    "Address": "Room 861",
    "ReceiveNewsLetters": true,
    "CountryID": "206418E0-F767-4689-BAC9-B0AA7696E60A"
  },
  {
    "PersonID": "B4E88AFA-BA23-4861-BC66-2DEEBC899239",
    "PersonName": "Brana Yarrow",
    "Email": "byarrow4@utexas.edu",
    "DateOfBirth": "2013-09-15",
    "Gender": "Female",
    "Address": "2nd Floor",
    "ReceiveNewsLetters": true,
    "CountryID": "F7F1E057-CC8D-4C34-B03F-32387397DAA2"
  },
  {
    "PersonID": "3CD4AD95-B7D4-43A9-B1A8-C09A3FFE8612",
    "PersonName": "Nicola McCullen",
    "Email": "nmccullen5@national.com",
    "DateOfBirth": "2024-04-17",
    "Gender": "Female",
    "Address": "Suite 59",
    "ReceiveNewsLetters": false,
    "CountryID": "206418E0-F767-4689-BAC9-B0AA7696E60A"
  },
  {
    "PersonID": "0ECABF09-8D29-4CAB-9593-FFDA5C1016F0",
    "PersonName": "Peyter Harman",
    "Email": "pharman4@github.com",
    "DateOfBirth": "1995-08-02",
    "Gender": "Male",
    "Address": "PO Box 53534",
    "ReceiveNewsLetters": false,
    "CountryID": "148FECC0-F5AA-43A1-9744-1DA4289C7A5A"
  },
  {
    "PersonID": "1884CF5F-9CAC-4D2E-8407-AE688F39ADC8",
    "PersonName": "Erroll Thoma",
    "Email": "ethoma6@mozilla.com",
    "DateOfBirth": "2006-07-17",
    "Gender": "Male",
    "Address": "Room 1638",
    "ReceiveNewsLetters": false,
    "CountryID": "206418E0-F767-4689-BAC9-B0AA7696E60A"
  },
  {
    "PersonID": "B32C879F-C578-4F6F-B6A6-DE5069AE2F4B",
    "PersonName": "Serge Ewebank",
    "Email": "sewebank7@blogs.com",
    "DateOfBirth": "2003-10-03",
    "Gender": "Male",
    "Address": "Apt 1481",
    "ReceiveNewsLetters": true,
    "CountryID": "0C5B9025-A178-422F-9772-B83CF42F3FBA"
  },
  {
    "PersonID": "47F724A7-7851-46F5-8B1C-C3F3B9D29EB9",
    "PersonName": "Boothe Chiverton",
    "Email": "bchiverton2@ucsd.edu",
    "DateOfBirth": "1990-04-06",
    "Gender": "Other",
    "Address": "5th Floor",
    "ReceiveNewsLetters": true,
    "CountryID": "B7D4A259-C1DF-42A1-B9CB-1D833D1580A3"
  }
]
